README.rst
setup.py
pitools/__init__.py
pitools/pi_process.py
pitools/utils.py
pitools.egg-info/PKG-INFO
pitools.egg-info/SOURCES.txt
pitools.egg-info/dependency_links.txt
pitools.egg-info/entry_points.txt
pitools.egg-info/requires.txt
pitools.egg-info/top_level.txt
pitools/launch/__init__.py
pitools/launch/do.py
pitools/launch/runfunction.py
pitools/log/__init__.py
pitools/modules/__init__.py
pitools/modules/imputation.py
pitools/modules/phasing.py
pitools/tools/__init__.py
pitools/tools/check.py
pitools/tools/eagle.py
pitools/tools/minimac3.py