Metadata-Version: 1.2
Name: pitools
Version: 1.0.0
Summary: pitools: A python program for phasing and imputation NGS data.
Home-page: https://github.com/ShujiaHuang/pitools
Author: Shujia Huang
Author-email: huangshujia9@gmail.com
Maintainer: Shujia Huang
Maintainer-email: huangshujia9@gmail.com
License: BSD (3-clause)
Download-URL: https://github.com/ShujiaHuang/pitools
Platform: UNKNOWN
Classifier: Intended Audience :: Science/Research
Classifier: Programming Language :: Python :: 2.7
Classifier: Programming Language :: Python :: 3.7
Classifier: License :: OSI Approved :: BSD License
Classifier: Topic :: Scientific/Engineering :: Bio-Informatics
Classifier: Operating System :: POSIX
Classifier: Operating System :: POSIX :: Linux
